vectormd/__init__.py
vectormd/vmd.py
VectorMD-0.1.dist-info/LICENSE
VectorMD-0.1.dist-info/METADATA
VectorMD-0.1.dist-info/WHEEL
VectorMD-0.1.dist-info/entry_points.txt
VectorMD-0.1.dist-info/top_level.txt
VectorMD-0.1.dist-info/RECORD
